KeyisBVMHost/__init__.py
KeyisBVMHost/_app.py
KeyisBVMHost/_f.py
keyisbvmhost-0.0.40.dist-info/METADATA
keyisbvmhost-0.0.40.dist-info/WHEEL
keyisbvmhost-0.0.40.dist-info/top_level.txt
keyisbvmhost-0.0.40.dist-info/RECORD
