Metadata-Version: 2.4
Name: KeyisBVMHost
Version: 0.0.40
Summary: KeyisBVMHost
Home-page: https://github.com/KeyisB/KeyisBVMHost
Author: KeyisB
Author-email: keyisb.pip@gmail.com
License: GN License v1.0
Classifier: Programming Language :: Python :: 3
Classifier: Operating System :: OS Independent
Requires-Python: >=3.12
Dynamic: author
Dynamic: author-email
Dynamic: classifier
Dynamic: description
Dynamic: description-content-type
Dynamic: home-page
Dynamic: license
Dynamic: requires-python
Dynamic: summary
